numpy_quaddtype/__init__.py
numpy_quaddtype/_quaddtype_main.cpython-313-x86_64-linux-gnu.so
numpy_quaddtype.libs/libgomp-e985bcbb.so.1.0.0
numpy_quaddtype-0.2.1.dist-info/LICENSE
numpy_quaddtype-0.2.1.dist-info/METADATA
numpy_quaddtype-0.2.1.dist-info/WHEEL
numpy_quaddtype-0.2.1.dist-info/RECORD
