Metadata-Version: 2.1
Name: numpy_quaddtype
Version: 0.2.1
Summary: Quad (128-bit) float dtype for numpy
Author-Email: Swayam Singh <singhswayam008@gmail.com>
License: Copyright (c) 2022, NumPy Developers.
Requires-Python: >=3.10.0
Requires-Dist: numpy
Provides-Extra: test
Requires-Dist: pytest; extra == "test"
Requires-Dist: pytest-run-parallel; extra == "test"
